{
    "data": {
        "processes_created": [
            "${SamplePath}\\f931e3e6fbcfa39dae313e63a7e0d3ec687f61a325d3be6aa954273e65bde334.exe",
            "%SAMPLEPATH%\\f931e3e6fbcfa39dae313e63a7e0d3ec687f61a325d3be6aa954273e65bde334.exe"
        ],
        "processes_terminated": [
            "${SamplePath}\\f931e3e6fbcfa39dae313e63a7e0d3ec687f61a325d3be6aa954273e65bde334.exe",
            "%SAMPLEPATH%\\f931e3e6fbcfa39dae313e63a7e0d3ec687f61a325d3be6aa954273e65bde334.exe",
            "C:\\Windows\\System32\\wuapihost.exe",
            "C:\\Documents and Settings\\Administrator\\Local Settings\\Temp\\EB93A6\\996E.exe"
        ],
        "command_executions": [
            "\"${SamplePath}\\f931e3e6fbcfa39dae313e63a7e0d3ec687f61a325d3be6aa954273e65bde334.exe\" ",
            "\"%SAMPLEPATH%\\f931e3e6fbcfa39dae313e63a7e0d3ec687f61a325d3be6aa954273e65bde334.exe\" ",
            " "
        ],
        "verdicts": [
            "MALWARE"
        ],
        "files_opened": [
            "C:\\WINDOWS\\system32\\winime32.dll",
            "C:\\WINDOWS\\system32\\ws2_32.dll",
            "C:\\WINDOWS\\system32\\ws2help.dll",
            "C:\\WINDOWS\\system32\\psapi.dll",
            "C:\\WINDOWS\\system32\\imm32.dll",
            "C:\\WINDOWS\\system32\\lpk.dll",
            "C:\\WINDOWS\\system32\\usp10.dll",
            "C:\\WINDOWS\\system32\\iphlpapi.dll",
            "C:\\Users\\user\\Desktop\\file.exe",
            "C:\\Windows\\AppPatch\\sysmain.sdb",
            "C:\\Windows\\SysWOW64\\ADVAPI32.dll",
            "C:\\Windows\\SysWOW64\\CRYPTBASE.dll",
            "C:\\Windows\\SysWOW64\\GDI32.dll",
            "C:\\Windows\\SysWOW64\\IMM32.DLL",
            "C:\\Windows\\SysWOW64\\KERNEL32.DLL",
            "C:\\Windows\\SysWOW64\\KERNELBASE.dll",
            "C:\\Windows\\SysWOW64\\MPR.dll",
            "C:\\Windows\\SysWOW64\\RPCRT4.dll",
            "C:\\Windows\\SysWOW64\\SspiCli.dll",
            "C:\\Windows\\SysWOW64\\USER32.dll",
            "C:\\Windows\\SysWOW64\\WS2_32.dll",
            "C:\\Windows\\SysWOW64\\apphelp.dll",
            "C:\\Windows\\SysWOW64\\bcryptPrimitives.dll",
            "C:\\Windows\\SysWOW64\\gdi32full.dll",
            "C:\\Windows\\SysWOW64\\iphlpapi.dll",
            "C:\\Windows\\SysWOW64\\msvcp_win.dll",
            "C:\\Windows\\SysWOW64\\msvcrt.dll",
            "C:\\Windows\\SysWOW64\\ntdll.dll",
            "C:\\Windows\\SysWOW64\\sechost.dll",
            "C:\\Windows\\SysWOW64\\ucrtbase.dll",
            "C:\\Windows\\SysWOW64\\win32u.dll"
        ],
        "processes_tree": [
            {
                "process_id": "400",
                "name": "\"${SamplePath}\\f931e3e6fbcfa39dae313e63a7e0d3ec687f61a325d3be6aa954273e65bde334.exe\" "
            },
            {
                "process_id": "3996",
                "name": "%WINDIR%\\explorer.exe",
                "children": [
                    {
                        "process_id": "3748",
                        "name": "%SAMPLEPATH%\\f931e3e6fbcfa39dae313e63a7e0d3ec687f61a325d3be6aa954273e65bde334.exe"
                    }
                ]
            },
            {
                "process_id": "264",
                "name": "****.exe"
            },
            {
                "process_id": "1532",
                "name": "****.exe"
            },
            {
                "process_id": "348",
                "name": "****.exe"
            },
            {
                "process_id": "1400",
                "name": "****.exe"
            },
            {
                "process_id": "1300",
                "name": "****.exe"
            },
            {
                "process_id": "184",
                "name": "****.exe"
            },
            {
                "process_id": "1616",
                "name": "****.exe"
            },
            {
                "process_id": "1908",
                "name": "****.exe"
            },
            {
                "process_id": "1896",
                "name": "****.exe"
            },
            {
                "process_id": "1308",
                "name": "****.exe"
            },
            {
                "process_id": "7840",
                "name": "\"C:\\Users\\user\\Desktop\\file.exe\" "
            }
        ],
        "mitre_attack_techniques": [
            {
                "id": "T1082",
                "severity": "IMPACT_SEVERITY_INFO",
                "signature_description": "Reads software policies"
            }
        ],
        "files_deleted": [
            "C:\\ProgramData\\Microsoft\\Windows\\WER\\Temp\\WERE186.tmp.WERInternalMetadata.xml",
            "C:\\ProgramData\\Microsoft\\Windows\\WER\\Temp\\WERE2ED.tmp.csv",
            "C:\\ProgramData\\Microsoft\\Windows\\WER\\Temp\\WERE32D.tmp.txt",
            "C:\\ProgramData\\Microsoft\\Windows\\WER\\Temp\\WERF3A8.tmp.WERInternalMetadata.xml",
            "C:\\ProgramData\\Microsoft\\Windows\\WER\\Temp\\WERF3B8.tmp.csv",
            "C:\\ProgramData\\Microsoft\\Windows\\WER\\Temp\\WERF3C9.tmp.txt",
            "C:\\Windows\\System32\\spp\\store\\2.0\\cache\\cache.dat"
        ],
        "ip_traffic": [
            {
                "destination_ip": "a83f:8110:6c00:7500:6d00:6500:3100:5c00",
                "destination_port": 53,
                "transport_layer_protocol": "UDP"
            },
            {
                "destination_ip": "20.99.184.37",
                "destination_port": 443,
                "transport_layer_protocol": "TCP"
            }
        ],
        "registry_keys_opened": [
            "\\Registry\\Machine\\Software\\Microsoft\\Windows NT\\CurrentVersion\\Image File Execution Options\\996E.exe",
            "\\Registry\\MACHINE\\System\\CurrentControlSet\\Control\\SafeBoot\\Option",
            "\\Registry\\Machine\\Software\\Policies\\Microsoft\\Windows\\Safer\\CodeIdentifiers",
            "\\REGISTRY\\MACHINE\\SOFTWARE\\Policies\\Microsoft\\Windows\\Safer\\CodeIdentifiers\\TransparentEnabled",
            "\\REGISTRY\\USER\\S-1-5-21-1482476501-1645522239-1417001333-500\\Software\\Policies\\Microsoft\\Windows\\Safer\\CodeIdentifiers",
            "\\Registry\\Machine\\Software\\Microsoft\\Windows NT\\CurrentVersion\\Image File Execution Options\\MPR.dll",
            "\\Registry\\Machine\\Software\\Microsoft\\Windows NT\\CurrentVersion\\Image File Execution Options\\iphlpapi.dll",
            "\\Registry\\Machine\\Software\\Microsoft\\Windows NT\\CurrentVersion\\Image File Execution Options\\ntdll.dll",
            "\\Registry\\Machine\\Software\\Microsoft\\Windows NT\\CurrentVersion\\Image File Execution Options\\KERNEL32.dll",
            "\\Registry\\Machine\\Software\\Microsoft\\Windows NT\\CurrentVersion\\Image File Execution Options\\GDI32.dll",
            "\\Registry\\Machine\\Software\\Microsoft\\Windows NT\\CurrentVersion\\Image File Execution Options\\USER32.dll",
            "\\Registry\\Machine\\Software\\Microsoft\\Windows NT\\CurrentVersion\\Image File Execution Options\\Secur32.dll",
            "\\Registry\\Machine\\Software\\Microsoft\\Windows NT\\CurrentVersion\\Image File Execution Options\\RPCRT4.dll",
            "\\Registry\\Machine\\Software\\Microsoft\\Windows NT\\CurrentVersion\\Image File Execution Options\\ADVAPI32.dll",
            "\\Registry\\Machine\\Software\\Microsoft\\Windows NT\\CurrentVersion\\Image File Execution Options\\msvcrt.dll",
            "\\Registry\\Machine\\Software\\Microsoft\\Windows NT\\CurrentVersion\\Image File Execution Options\\WS2HELP.dll",
            "\\Registry\\Machine\\Software\\Microsoft\\Windows NT\\CurrentVersion\\Image File Execution Options\\WS2_32.dll",
            "\\Registry\\Machine\\Software\\Microsoft\\Windows NT\\CurrentVersion\\Image File Execution Options\\SHLWAPI.dll",
            "\\Registry\\Machine\\Software\\Microsoft\\Windows NT\\CurrentVersion\\Image File Execution Options\\PSAPI.DLL",
            "\\Registry\\Machine\\Software\\Microsoft\\Windows NT\\CurrentVersion\\Image File Execution Options\\winime32.dll",
            "\\Registry\\Machine\\Software\\Microsoft\\Windows NT\\CurrentVersion\\Image File Execution Options\\IMM32.DLL",
            "\\Registry\\Machine\\Software\\Microsoft\\Windows NT\\CurrentVersion\\Image File Execution Options\\USP10.dll",
            "\\Registry\\Machine\\Software\\Microsoft\\Windows NT\\CurrentVersion\\Image File Execution Options\\LPK.DLL",
            "\\REGISTRY\\MACHINE\\Software\\Microsoft\\Windows NT\\CurrentVersion\\Image File Execution Options\\996E.exe\\RpcThreadPoolThrottle",
            "\\REGISTRY\\MACHINE\\Software\\Policies\\Microsoft\\Windows NT\\Rpc",
            "HKEY_CURRENT_USER\\Software\\Microsoft\\Windows\\CurrentVersion\\Explorer\\Shell Folders",
            "HKEY_LOCAL_MACHINE\\SOFTWARE\\Microsoft\\Windows NT\\CurrentVersion\\Image File Execution Options\\DllNXOptions",
            "HKEY_LOCAL_MACHINE\\SOFTWARE\\Microsoft\\Windows NT\\CurrentVersion\\Image File Execution Options\\file.exe",
            "HKEY_LOCAL_MACHINE\\SYSTEM\\ControlSet001\\Control\\MUI\\UILanguages\\en-US",
            "HKEY_LOCAL_MACHINE\\SYSTEM\\CurrentControlSet\\Control\\Nls\\CustomLocale",
            "HKEY_LOCAL_MACHINE\\SYSTEM\\CurrentControlSet\\Control\\Session Manager",
            "HKEY_LOCAL_MACHINE\\SYSTEM\\CurrentControlSet\\Control\\Session Manager\\Segment Heap",
            "HKEY_LOCAL_MACHINE\\SYSTEM\\CurrentControlSet\\Policies\\Microsoft\\Cryptography\\Configuration",
            "HKEY_LOCAL_MACHINE\\Software\\Microsoft\\Windows NT\\CurrentVersion\\AppCompatFlags\\Disable8And16BitMitigation",
            "HKEY_LOCAL_MACHINE\\Software\\Microsoft\\Wow64\\x86",
            "HKEY_LOCAL_MACHINE\\Software\\WOW6432Node\\Microsoft\\Windows NT\\CurrentVersion\\AppCompatFlags",
            "HKEY_LOCAL_MACHINE\\Software\\WOW6432Node\\Microsoft\\Windows NT\\CurrentVersion\\GRE_Initialize",
            "HKEY_LOCAL_MACHINE\\Software\\WOW6432Node\\Microsoft\\Windows NT\\CurrentVersion\\Image File Execution Options",
            "HKEY_LOCAL_MACHINE\\Software\\WOW6432Node\\Microsoft\\Windows NT\\CurrentVersion\\Windows",
            "HKEY_LOCAL_MACHINE\\Software\\WOW6432Node\\Policies\\Microsoft\\MUI\\Settings",
            "HKEY_LOCAL_MACHINE\\Software\\WOW6432Node\\Policies\\Microsoft\\Windows\\Display",
            "HKEY_LOCAL_MACHINE\\Software\\WOW6432Node\\Policies\\Microsoft\\Windows\\Safer\\CodeIdentifiers",
            "HKEY_LOCAL_MACHINE\\System\\CurrentControlSet\\Control\\FileSystem\\",
            "HKEY_LOCAL_MACHINE\\System\\CurrentControlSet\\Control\\Lsa",
            "HKEY_LOCAL_MACHINE\\System\\CurrentControlSet\\Control\\Lsa\\FipsAlgorithmPolicy",
            "HKEY_LOCAL_MACHINE\\System\\CurrentControlSet\\Control\\MUI\\Settings\\LanguageConfiguration",
            "HKEY_LOCAL_MACHINE\\System\\CurrentControlSet\\Control\\MUI\\UILanguages",
            "HKEY_LOCAL_MACHINE\\System\\CurrentControlSet\\Control\\MUI\\UILanguages\\PendingDelete",
            "HKEY_LOCAL_MACHINE\\System\\CurrentControlSet\\Control\\NLS\\Language",
            "HKEY_LOCAL_MACHINE\\System\\CurrentControlSet\\Control\\Nls\\Sorting\\Versions",
            "HKEY_LOCAL_MACHINE\\System\\CurrentControlSet\\Control\\SafeBoot\\Option",
            "HKEY_LOCAL_MACHINE\\System\\CurrentControlSet\\Control\\Session Manager",
            "HKEY_LOCAL_MACHINE\\System\\CurrentControlSet\\Control\\Srp\\GP\\DLL",
            "HKEY_LOCAL_MACHINE\\System\\CurrentControlSet\\Control\\Terminal Server",
            "HKEY_LOCAL_MACHINE\\system\\CurrentControlSet\\control\\NetworkProvider\\HwOrder",
            "HKEY_LOCAL_MACHINE\\system\\CurrentControlSet\\control\\NetworkProvider\\ProviderOrder"
        ],
        "tags": [
            "IDLE"
        ],
        "modules_loaded": [
            "${SamplePath}\\f931e3e6fbcfa39dae313e63a7e0d3ec687f61a325d3be6aa954273e65bde334.exe",
            "C:\\Windows\\System32\\ntdll.dll",
            "C:\\Windows\\SysWOW64\\ntdll.dll",
            "C:\\Windows\\System32\\wow64.dll",
            "C:\\Windows\\System32\\wow64win.dll",
            "C:\\Windows\\System32\\wow64cpu.dll",
            "C:\\Windows\\System32\\kernel32.dll",
            "C:\\Windows\\SysWOW64\\kernel32.dll",
            "C:\\Windows\\System32\\user32.dll",
            "C:\\Windows\\SysWOW64\\KernelBase.dll",
            "C:\\Windows\\SysWOW64\\user32.dll",
            "C:\\Windows\\SysWOW64\\gdi32.dll",
            "C:\\Windows\\SysWOW64\\lpk.dll",
            "C:\\Windows\\SysWOW64\\usp10.dll",
            "C:\\Windows\\SysWOW64\\msvcrt.dll",
            "C:\\Windows\\SysWOW64\\advapi32.dll",
            "C:\\Windows\\SysWOW64\\sechost.dll",
            "C:\\Windows\\SysWOW64\\rpcrt4.dll",
            "C:\\Windows\\SysWOW64\\sspicli.dll",
            "C:\\Windows\\SysWOW64\\cryptbase.dll",
            "C:\\Windows\\SysWOW64\\ws2_32.dll",
            "C:\\Windows\\SysWOW64\\nsi.dll",
            "C:\\Windows\\SysWOW64\\mpr.dll",
            "C:\\Windows\\SysWOW64\\IPHLPAPI.DLL",
            "C:\\Windows\\SysWOW64\\winnsi.dll",
            "C:\\Windows\\SysWOW64\\imm32.dll",
            "C:\\Windows\\SysWOW64\\msctf.dll",
            "C:\\Windows\\SysWOW64\\shell32.dll",
            "C:\\Windows\\SysWOW64\\shlwapi.dll",
            "C:\\Windows\\SysWOW64\\ole32.dll",
            "C:\\Windows\\winsxs\\x86_microsoft.windows.gdiplus_6595b64144ccf1df_1.1.7601.24203_none_5c030043a0118fbf\\GdiPlus.dll",
            "C:\\Windows\\SysWOW64\\dbghelp.dll",
            "C:\\Windows\\SysWOW64\\psapi.dll",
            "C:\\Windows\\SysWOW64\\oleaut32.dll",
            "C:\\Windows\\SysWOW64\\setupapi.dll",
            "C:\\Windows\\SysWOW64\\cfgmgr32.dll",
            "C:\\Windows\\SysWOW64\\devobj.dll",
            "C:\\Windows\\SysWOW64\\api-ms-win-core-synch-l1-2-0.DLL",
            "C:\\Windows\\SysWOW64\\imagehlp.dll",
            "C:\\Windows\\SysWOW64\\version.dll",
            "%SAMPLEPATH%\\f931e3e6fbcfa39dae313e63a7e0d3ec687f61a325d3be6aa954273e65bde334.exe",
            "rpcrt4.dll"
        ],
        "files_dropped": [
            {
                "path": "C:\\ProgramData\\Microsoft\\Windows\\WER\\Temp\\WERE186.tmp"
            },
            {
                "path": "C:\\ProgramData\\Microsoft\\Windows\\WER\\Temp\\WERE186.tmp.WERInternalMetadata.xml"
            },
            {
                "path": "C:\\ProgramData\\Microsoft\\Windows\\WER\\Temp\\WERE2ED.tmp"
            },
            {
                "path": "C:\\ProgramData\\Microsoft\\Windows\\WER\\Temp\\WERE2ED.tmp.csv"
            },
            {
                "path": "C:\\ProgramData\\Microsoft\\Windows\\WER\\Temp\\WERE32D.tmp"
            },
            {
                "path": "C:\\ProgramData\\Microsoft\\Windows\\WER\\Temp\\WERE32D.tmp.txt"
            },
            {
                "path": "C:\\Windows\\System32\\spp\\store\\2.0\\data.dat.tmp"
            },
            {
                "path": "C:\\ProgramData\\Microsoft\\Windows\\WER\\Temp\\WERF3A8.tmp"
            },
            {
                "path": "C:\\ProgramData\\Microsoft\\Windows\\WER\\Temp\\WERF3A8.tmp.WERInternalMetadata.xml"
            },
            {
                "path": "C:\\ProgramData\\Microsoft\\Windows\\WER\\Temp\\WERF3B8.tmp"
            },
            {
                "path": "C:\\ProgramData\\Microsoft\\Windows\\WER\\Temp\\WERF3B8.tmp.csv"
            },
            {
                "path": "C:\\ProgramData\\Microsoft\\Windows\\WER\\Temp\\WERF3C9.tmp"
            },
            {
                "path": "C:\\ProgramData\\Microsoft\\Windows\\WER\\Temp\\WERF3C9.tmp.txt"
            },
            {
                "path": "C:\\Windows\\System32\\spp\\store\\2.0\\cache\\cache.dat"
            }
        ],
        "attack_techniques": {
            "T1082": [
                {
                    "severity": "INFO",
                    "description": "Reads software policies"
                }
            ]
        }
    }
}